{"metadata":{"usedHelpers":[],"marked":[],"modules":{"imports":[],"exports":{"exported":[],"specifiers":[]}}},"options":{"filename":"imports/api/users.js","filenameRelative":"imports/api/users.js","env":{"development":{"plugins":[]}},"retainLines":false,"highlightCode":true,"suppressDeprecationMessages":false,"presets":[],"plugins":[[[],{"generateLetDeclarations":true,"enforceStrictMode":false}],[[],null],[[],{"polyfill":false}],[[],null],[[],null],[[],null],[[],{"allowTopLevelThis":true,"strict":false,"loose":true}],[[],null],[[],null],[[],null],[[],null],[[],null],[[],null],[[],null],[[],null],[[],null],[[],null],[[],null],[[],null],[[],{"loose":true}],[[],{"loose":true}],[[],null],[[],{"loose":true}],[[],null],[[],null],[[],null],[[],null],[[],null],[[],null],[[],{"loose":true}],[[],null],[[],null],[[],null],[[],null],[[],null],[[],null],[[],null]],"ignore":[],"code":true,"metadata":true,"ast":true,"comments":true,"compact":false,"minified":false,"sourceMap":true,"sourceMaps":true,"sourceMapTarget":"imports/api/users.js.map","sourceFileName":"imports/api/users.js","babelrc":false,"sourceType":"module","moduleIds":false,"passPerPreset":false,"parserOpts":false,"generatorOpts":false,"basename":"users"},"ignored":false,"code":"","map":{"version":3,"sources":[],"names":[],"mappings":"","file":"imports/api/users.js.map","sourcesContent":[]},"hash":"1ec933f4239a94707dcecf6ca6beb3cd8569563c"}
